ultra_auth/__init__.py
ultra_auth/about.py
ultra_auth/tasks.py
ultra_auth/udns.py
ultra_auth-0.1.3.5.dist-info/LICENSE.md
ultra_auth-0.1.3.5.dist-info/METADATA
ultra_auth-0.1.3.5.dist-info/WHEEL
ultra_auth-0.1.3.5.dist-info/top_level.txt
ultra_auth-0.1.3.5.dist-info/RECORD
