Metadata-Version: 2.1
Name: ultra_auth
Version: 0.1.3.5
Summary: A compact auth client for UltraDNS
Home-page: https://github.com/sbarbvett/ultra_auth
Author: Shane Barbetta
Author-email: shane@barbetta.me
Classifier: Programming Language :: Python :: 3
Classifier: License :: OSI Approved :: MIT License
Classifier: Operating System :: OS Independent
Requires-Python: >=3.6
License-File: LICENSE.md
Requires-Dist: requests >=2.25.1
